Metadata-Version: 2.1
Name: devtools-json-schema
Version: 1.0.1
Summary: JSON Schema validator
Home-page: https://devtools.at/tools/json-schema-validator
Author: DevTools.at
Author-email: hello@devtools.at
Project-URL: Homepage, https://devtools.at/tools/json-schema-validator
Project-URL: Repository, https://github.com/devtools-at/json-schema-validator
Classifier: Development Status :: 4 - Beta
Classifier: Intended Audience :: Developers
Classifier: License :: OSI Approved :: MIT License
Classifier: Programming Language :: Python :: 3
Requires-Python: >=3.8
